{
  "ordem": [
    "Beda",
    "AH",
    "Rodrigo",
    "Romanelli",
    "Su",
    "Mané",
    "Pedro",
    "Caio",
    "Paulo",
    "Mauro",
    "Biral",
    "Kim",
    "Camps"
  ],
  "ordem_anterior": [
    "Beda",
    "AH",
    "Rodrigo",
    "Romanelli",
    "Su",
    "Mané",
    "Paulo",
    "Pedro",
    "Caio",
    "Mauro",
    "Biral",
    "Kim",
    "Camps"
  ],
  "pontos": {
    "Beda": 197,
    "AH": 192,
    "Rodrigo": 188,
    "Romanelli": 183,
    "Su": 179,
    "Mané": 176,
    "Pedro": 175,
    "Caio": 174,
    "Paulo": 173,
    "Mauro": 171,
    "Biral": 164,
    "Kim": 108,
    "Camps": 97
  },
  "avancos": {
    "74": 2,
    "75": 2,
    "88": 2
  },
  "atualizado_em": "2026-07-06T13:43:44.577764-03:00"
}